{
  "_format": "hh-sol-cache-2",
  "files": {
    "/Users/antonasso/programming/opyn/perp-vault-templates/contracts/core/OpynPerpVault.sol": {
      "lastModificationDate": 1623424904389,
      "contentHash": "11d40f2a216903c748ee429bdae18ea7",
      "sourceName": "contracts/core/OpynPerpVault.sol",
      "solcConfig": {
        "version": "0.7.6",
        "settings": {
          "optimizer": {
            "enabled": false,
            "runs": 200
          },
          "outputSelection": {
            "*": {
              "*": [
                "abi",
                "evm.bytecode",
                "evm.deployedBytecode",
                "evm.methodIdentifiers"
              ],
              "": [
                "ast"
              ]
            }
          }
        }
      },
      "imports": [
        "@openzeppelin/contracts-upgradeable/utils/ReentrancyGuardUpgradeable.sol",
        "@openzeppelin/contracts-upgradeable/token/ERC20/ERC20Upgradeable.sol",
        "@openzeppelin/contracts-upgradeable/access/OwnableUpgradeable.sol",
        "../interfaces/IAction.sol",
        "@openzeppelin/contracts/token/ERC20/IERC20.sol",
        "../interfaces/IWETH.sol",
        "@openzeppelin/contracts/token/ERC20/SafeERC20.sol",
        "@openzeppelin/contracts/math/SafeMath.sol"
      ],
      "versionPragmas": [
        ">=0.7.2"
      ],
      "artifacts": [
        "OpynPerpVault"
      ]
    },
    "/Users/antonasso/programming/opyn/perp-vault-templates/node_modules/@openzeppelin/contracts-upgradeable/utils/ReentrancyGuardUpgradeable.sol": {
      "lastModificationDate": 1622516807444,
      "contentHash": "008d2d730bc1f24f3c0fafa29b7a0bd2",
      "sourceName": "@openzeppelin/contracts-upgradeable/utils/ReentrancyGuardUpgradeable.sol",
      "solcConfig": {
        "version": "0.7.6",
        "settings": {
          "optimizer": {
            "enabled": false,
            "runs": 200
          },
          "outputSelection": {
            "*": {
              "*": [
                "abi",
                "evm.bytecode",
                "evm.deployedBytecode",
                "evm.methodIdentifiers"
              ],
              "": [
                "ast"
              ]
            }
          }
        }
      },
      "imports": [
        "../proxy/Initializable.sol"
      ],
      "versionPragmas": [
        ">=0.6.0 <0.8.0"
      ],
      "artifacts": [
        "ReentrancyGuardUpgradeable"
      ]
    },
    "/Users/antonasso/programming/opyn/perp-vault-templates/node_modules/@openzeppelin/contracts-upgradeable/token/ERC20/ERC20Upgradeable.sol": {
      "lastModificationDate": 1622516807040,
      "contentHash": "4404d773c16609e9c316b0acaa487556",
      "sourceName": "@openzeppelin/contracts-upgradeable/token/ERC20/ERC20Upgradeable.sol",
      "solcConfig": {
        "version": "0.7.6",
        "settings": {
          "optimizer": {
            "enabled": false,
            "runs": 200
          },
          "outputSelection": {
            "*": {
              "*": [
                "abi",
                "evm.bytecode",
                "evm.deployedBytecode",
                "evm.methodIdentifiers"
              ],
              "": [
                "ast"
              ]
            }
          }
        }
      },
      "imports": [
        "../../utils/ContextUpgradeable.sol",
        "./IERC20Upgradeable.sol",
        "../../math/SafeMathUpgradeable.sol",
        "../../proxy/Initializable.sol"
      ],
      "versionPragmas": [
        ">=0.6.0 <0.8.0"
      ],
      "artifacts": [
        "ERC20Upgradeable"
      ]
    },
    "/Users/antonasso/programming/opyn/perp-vault-templates/node_modules/@openzeppelin/contracts-upgradeable/access/OwnableUpgradeable.sol": {
      "lastModificationDate": 1622516807390,
      "contentHash": "91a7735bfcbb48c7482f10f1083a8ed8",
      "sourceName": "@openzeppelin/contracts-upgradeable/access/OwnableUpgradeable.sol",
      "solcConfig": {
        "version": "0.7.6",
        "settings": {
          "optimizer": {
            "enabled": false,
            "runs": 200
          },
          "outputSelection": {
            "*": {
              "*": [
                "abi",
                "evm.bytecode",
                "evm.deployedBytecode",
                "evm.methodIdentifiers"
              ],
              "": [
                "ast"
              ]
            }
          }
        }
      },
      "imports": [
        "../utils/ContextUpgradeable.sol",
        "../proxy/Initializable.sol"
      ],
      "versionPragmas": [
        ">=0.6.0 <0.8.0"
      ],
      "artifacts": [
        "OwnableUpgradeable"
      ]
    },
    "/Users/antonasso/programming/opyn/perp-vault-templates/contracts/interfaces/IAction.sol": {
      "lastModificationDate": 1623424904546,
      "contentHash": "f0922f908ba3a42c806ba287da1774b5",
      "sourceName": "contracts/interfaces/IAction.sol",
      "solcConfig": {
        "version": "0.7.6",
        "settings": {
          "optimizer": {
            "enabled": false,
            "runs": 200
          },
          "outputSelection": {
            "*": {
              "*": [
                "abi",
                "evm.bytecode",
                "evm.deployedBytecode",
                "evm.methodIdentifiers"
              ],
              "": [
                "ast"
              ]
            }
          }
        }
      },
      "imports": [],
      "versionPragmas": [
        ">=0.7.2"
      ],
      "artifacts": [
        "IAction"
      ]
    },
    "/Users/antonasso/programming/opyn/perp-vault-templates/node_modules/@openzeppelin/contracts/token/ERC20/IERC20.sol": {
      "lastModificationDate": 1622516807424,
      "contentHash": "e0a41531d159d3a32f84b7a3ecf9fabb",
      "sourceName": "@openzeppelin/contracts/token/ERC20/IERC20.sol",
      "solcConfig": {
        "version": "0.7.6",
        "settings": {
          "optimizer": {
            "enabled": false,
            "runs": 200
          },
          "outputSelection": {
            "*": {
              "*": [
                "abi",
                "evm.bytecode",
                "evm.deployedBytecode",
                "evm.methodIdentifiers"
              ],
              "": [
                "ast"
              ]
            }
          }
        }
      },
      "imports": [],
      "versionPragmas": [
        ">=0.6.0 <0.8.0"
      ],
      "artifacts": [
        "IERC20"
      ]
    },
    "/Users/antonasso/programming/opyn/perp-vault-templates/contracts/interfaces/IWETH.sol": {
      "lastModificationDate": 1623424904621,
      "contentHash": "2b3b21dea4a991a64f8c2d6f84813f51",
      "sourceName": "contracts/interfaces/IWETH.sol",
      "solcConfig": {
        "version": "0.7.6",
        "settings": {
          "optimizer": {
            "enabled": false,
            "runs": 200
          },
          "outputSelection": {
            "*": {
              "*": [
                "abi",
                "evm.bytecode",
                "evm.deployedBytecode",
                "evm.methodIdentifiers"
              ],
              "": [
                "ast"
              ]
            }
          }
        }
      },
      "imports": [],
      "versionPragmas": [
        ">=0.7.2"
      ],
      "artifacts": [
        "IWETH"
      ]
    },
    "/Users/antonasso/programming/opyn/perp-vault-templates/node_modules/@openzeppelin/contracts/token/ERC20/SafeERC20.sol": {
      "lastModificationDate": 1622516807649,
      "contentHash": "33e22842646d746e5c4124c2fdc051aa",
      "sourceName": "@openzeppelin/contracts/token/ERC20/SafeERC20.sol",
      "solcConfig": {
        "version": "0.7.6",
        "settings": {
          "optimizer": {
            "enabled": false,
            "runs": 200
          },
          "outputSelection": {
            "*": {
              "*": [
                "abi",
                "evm.bytecode",
                "evm.deployedBytecode",
                "evm.methodIdentifiers"
              ],
              "": [
                "ast"
              ]
            }
          }
        }
      },
      "imports": [
        "./IERC20.sol",
        "../../math/SafeMath.sol",
        "../../utils/Address.sol"
      ],
      "versionPragmas": [
        ">=0.6.0 <0.8.0"
      ],
      "artifacts": [
        "SafeERC20"
      ]
    },
    "/Users/antonasso/programming/opyn/perp-vault-templates/node_modules/@openzeppelin/contracts/math/SafeMath.sol": {
      "lastModificationDate": 1622516807656,
      "contentHash": "e03e12206057e809eb76c5f681170c32",
      "sourceName": "@openzeppelin/contracts/math/SafeMath.sol",
      "solcConfig": {
        "version": "0.7.6",
        "settings": {
          "optimizer": {
            "enabled": false,
            "runs": 200
          },
          "outputSelection": {
            "*": {
              "*": [
                "abi",
                "evm.bytecode",
                "evm.deployedBytecode",
                "evm.methodIdentifiers"
              ],
              "": [
                "ast"
              ]
            }
          }
        }
      },
      "imports": [],
      "versionPragmas": [
        ">=0.6.0 <0.8.0"
      ],
      "artifacts": [
        "SafeMath"
      ]
    },
    "/Users/antonasso/programming/opyn/perp-vault-templates/node_modules/@openzeppelin/contracts-upgradeable/proxy/Initializable.sol": {
      "lastModificationDate": 1622516807325,
      "contentHash": "71b3ac8d4da61bb6c6708c12f56e3c1f",
      "sourceName": "@openzeppelin/contracts-upgradeable/proxy/Initializable.sol",
      "solcConfig": {
        "version": "0.7.6",
        "settings": {
          "optimizer": {
            "enabled": false,
            "runs": 200
          },
          "outputSelection": {
            "*": {
              "*": [
                "abi",
                "evm.bytecode",
                "evm.deployedBytecode",
                "evm.methodIdentifiers"
              ],
              "": [
                "ast"
              ]
            }
          }
        }
      },
      "imports": [
        "../utils/AddressUpgradeable.sol"
      ],
      "versionPragmas": [
        ">=0.4.24 <0.8.0"
      ],
      "artifacts": [
        "Initializable"
      ]
    },
    "/Users/antonasso/programming/opyn/perp-vault-templates/node_modules/@openzeppelin/contracts-upgradeable/utils/AddressUpgradeable.sol": {
      "lastModificationDate": 1622516806710,
      "contentHash": "aa72beb3bf14f8394b4a8a292d66589c",
      "sourceName": "@openzeppelin/contracts-upgradeable/utils/AddressUpgradeable.sol",
      "solcConfig": {
        "version": "0.7.6",
        "settings": {
          "optimizer": {
            "enabled": false,
            "runs": 200
          },
          "outputSelection": {
            "*": {
              "*": [
                "abi",
                "evm.bytecode",
                "evm.deployedBytecode",
                "evm.methodIdentifiers"
              ],
              "": [
                "ast"
              ]
            }
          }
        }
      },
      "imports": [],
      "versionPragmas": [
        ">=0.6.2 <0.8.0"
      ],
      "artifacts": [
        "AddressUpgradeable"
      ]
    },
    "/Users/antonasso/programming/opyn/perp-vault-templates/node_modules/@openzeppelin/contracts-upgradeable/utils/ContextUpgradeable.sol": {
      "lastModificationDate": 1622516806757,
      "contentHash": "9f901c17a18eadc08042b6a510da3b7d",
      "sourceName": "@openzeppelin/contracts-upgradeable/utils/ContextUpgradeable.sol",
      "solcConfig": {
        "version": "0.7.6",
        "settings": {
          "optimizer": {
            "enabled": false,
            "runs": 200
          },
          "outputSelection": {
            "*": {
              "*": [
                "abi",
                "evm.bytecode",
                "evm.deployedBytecode",
                "evm.methodIdentifiers"
              ],
              "": [
                "ast"
              ]
            }
          }
        }
      },
      "imports": [
        "../proxy/Initializable.sol"
      ],
      "versionPragmas": [
        ">=0.6.0 <0.8.0"
      ],
      "artifacts": [
        "ContextUpgradeable"
      ]
    },
    "/Users/antonasso/programming/opyn/perp-vault-templates/node_modules/@openzeppelin/contracts-upgradeable/token/ERC20/IERC20Upgradeable.sol": {
      "lastModificationDate": 1622516807252,
      "contentHash": "6c8edd65243ec9d6eb91cc63cce2cd16",
      "sourceName": "@openzeppelin/contracts-upgradeable/token/ERC20/IERC20Upgradeable.sol",
      "solcConfig": {
        "version": "0.7.6",
        "settings": {
          "optimizer": {
            "enabled": false,
            "runs": 200
          },
          "outputSelection": {
            "*": {
              "*": [
                "abi",
                "evm.bytecode",
                "evm.deployedBytecode",
                "evm.methodIdentifiers"
              ],
              "": [
                "ast"
              ]
            }
          }
        }
      },
      "imports": [],
      "versionPragmas": [
        ">=0.6.0 <0.8.0"
      ],
      "artifacts": [
        "IERC20Upgradeable"
      ]
    },
    "/Users/antonasso/programming/opyn/perp-vault-templates/node_modules/@openzeppelin/contracts-upgradeable/math/SafeMathUpgradeable.sol": {
      "lastModificationDate": 1622516807503,
      "contentHash": "33cad0216fea16ce4baadc5603b84218",
      "sourceName": "@openzeppelin/contracts-upgradeable/math/SafeMathUpgradeable.sol",
      "solcConfig": {
        "version": "0.7.6",
        "settings": {
          "optimizer": {
            "enabled": false,
            "runs": 200
          },
          "outputSelection": {
            "*": {
              "*": [
                "abi",
                "evm.bytecode",
                "evm.deployedBytecode",
                "evm.methodIdentifiers"
              ],
              "": [
                "ast"
              ]
            }
          }
        }
      },
      "imports": [],
      "versionPragmas": [
        ">=0.6.0 <0.8.0"
      ],
      "artifacts": [
        "SafeMathUpgradeable"
      ]
    },
    "/Users/antonasso/programming/opyn/perp-vault-templates/node_modules/@openzeppelin/contracts/utils/Address.sol": {
      "lastModificationDate": 1622516806858,
      "contentHash": "7aa46886ff5abe7515496208a5e2ce5a",
      "sourceName": "@openzeppelin/contracts/utils/Address.sol",
      "solcConfig": {
        "version": "0.7.6",
        "settings": {
          "optimizer": {
            "enabled": false,
            "runs": 200
          },
          "outputSelection": {
            "*": {
              "*": [
                "abi",
                "evm.bytecode",
                "evm.deployedBytecode",
                "evm.methodIdentifiers"
              ],
              "": [
                "ast"
              ]
            }
          }
        }
      },
      "imports": [],
      "versionPragmas": [
        ">=0.6.2 <0.8.0"
      ],
      "artifacts": [
        "Address"
      ]
    },
    "/Users/antonasso/programming/opyn/perp-vault-templates/contracts/utils/GammaVaultUtils.sol": {
      "lastModificationDate": 1623424904974,
      "contentHash": "d46cc9db46c4e0ed8d02cc26bbb6cca3",
      "sourceName": "contracts/utils/GammaVaultUtils.sol",
      "solcConfig": {
        "version": "0.7.6",
        "settings": {
          "optimizer": {
            "enabled": false,
            "runs": 200
          },
          "outputSelection": {
            "*": {
              "*": [
                "abi",
                "evm.bytecode",
                "evm.deployedBytecode",
                "evm.methodIdentifiers"
              ],
              "": [
                "ast"
              ]
            }
          }
        }
      },
      "imports": [
        "@openzeppelin/contracts/token/ERC20/IERC20.sol",
        "@openzeppelin/contracts/token/ERC20/SafeERC20.sol",
        "@openzeppelin/contracts/math/SafeMath.sol",
        "../interfaces/IController.sol"
      ],
      "versionPragmas": [
        ">=0.7.2"
      ],
      "artifacts": [
        "GammaVaultUtils"
      ]
    },
    "/Users/antonasso/programming/opyn/perp-vault-templates/contracts/interfaces/IController.sol": {
      "lastModificationDate": 1623424904567,
      "contentHash": "70275581d18e97d7924f862ba6180910",
      "sourceName": "contracts/interfaces/IController.sol",
      "solcConfig": {
        "version": "0.7.6",
        "settings": {
          "optimizer": {
            "enabled": false,
            "runs": 200
          },
          "outputSelection": {
            "*": {
              "*": [
                "abi",
                "evm.bytecode",
                "evm.deployedBytecode",
                "evm.methodIdentifiers"
              ],
              "": [
                "ast"
              ]
            }
          }
        }
      },
      "imports": [],
      "versionPragmas": [
        ">=0.7.2"
      ],
      "artifacts": [
        "IController"
      ]
    },
    "/Users/antonasso/programming/opyn/perp-vault-templates/contracts/example-actions/ShortOToken.sol": {
      "lastModificationDate": 1623651555763,
      "contentHash": "dfc7340a3c6586ce7d9dc8278f084378",
      "sourceName": "contracts/example-actions/ShortOToken.sol",
      "solcConfig": {
        "version": "0.7.6",
        "settings": {
          "optimizer": {
            "enabled": false,
            "runs": 200
          },
          "outputSelection": {
            "*": {
              "*": [
                "abi",
                "evm.bytecode",
                "evm.deployedBytecode",
                "evm.methodIdentifiers"
              ],
              "": [
                "ast"
              ]
            }
          }
        }
      },
      "imports": [
        "@openzeppelin/contracts-upgradeable/access/OwnableUpgradeable.sol",
        "../utils/GammaVaultUtils.sol",
        "../utils/RollOverBase.sol",
        "../utils/AirswapUtils.sol",
        "../utils/AuctionUtils.sol",
        "../libraries/SwapTypes.sol",
        "@openzeppelin/contracts/token/ERC20/IERC20.sol",
        "@openzeppelin/contracts/token/ERC20/SafeERC20.sol",
        "@openzeppelin/contracts/math/SafeMath.sol",
        "../interfaces/IController.sol",
        "../interfaces/IAction.sol",
        "../interfaces/IOracle.sol",
        "../interfaces/IOToken.sol"
      ],
      "versionPragmas": [
        ">=0.7.2"
      ],
      "artifacts": [
        "ShortOToken"
      ]
    },
    "/Users/antonasso/programming/opyn/perp-vault-templates/contracts/utils/RollOverBase.sol": {
      "lastModificationDate": 1623424905017,
      "contentHash": "d6df81a131b07579fc32f7345d32430a",
      "sourceName": "contracts/utils/RollOverBase.sol",
      "solcConfig": {
        "version": "0.7.6",
        "settings": {
          "optimizer": {
            "enabled": false,
            "runs": 200
          },
          "outputSelection": {
            "*": {
              "*": [
                "abi",
                "evm.bytecode",
                "evm.deployedBytecode",
                "evm.methodIdentifiers"
              ],
              "": [
                "ast"
              ]
            }
          }
        }
      },
      "imports": [
        "@openzeppelin/contracts-upgradeable/access/OwnableUpgradeable.sol",
        "../interfaces/IWhitelist.sol"
      ],
      "versionPragmas": [
        ">=0.7.2"
      ],
      "artifacts": [
        "RollOverBase"
      ]
    },
    "/Users/antonasso/programming/opyn/perp-vault-templates/contracts/utils/AirswapUtils.sol": {
      "lastModificationDate": 1623424904823,
      "contentHash": "2da9da31b2f949f1d208aeb53b3a89f3",
      "sourceName": "contracts/utils/AirswapUtils.sol",
      "solcConfig": {
        "version": "0.7.6",
        "settings": {
          "optimizer": {
            "enabled": false,
            "runs": 200
          },
          "outputSelection": {
            "*": {
              "*": [
                "abi",
                "evm.bytecode",
                "evm.deployedBytecode",
                "evm.methodIdentifiers"
              ],
              "": [
                "ast"
              ]
            }
          }
        }
      },
      "imports": [
        "@openzeppelin/contracts/token/ERC20/IERC20.sol",
        "@openzeppelin/contracts/token/ERC20/SafeERC20.sol",
        "../interfaces/ISwap.sol",
        "../libraries/SwapTypes.sol"
      ],
      "versionPragmas": [
        ">=0.7.2"
      ],
      "artifacts": [
        "AirswapUtils"
      ]
    },
    "/Users/antonasso/programming/opyn/perp-vault-templates/contracts/utils/AuctionUtils.sol": {
      "lastModificationDate": 1623424904852,
      "contentHash": "26188ee4db4d1ef722c60dc80f9093b3",
      "sourceName": "contracts/utils/AuctionUtils.sol",
      "solcConfig": {
        "version": "0.7.6",
        "settings": {
          "optimizer": {
            "enabled": false,
            "runs": 200
          },
          "outputSelection": {
            "*": {
              "*": [
                "abi",
                "evm.bytecode",
                "evm.deployedBytecode",
                "evm.methodIdentifiers"
              ],
              "": [
                "ast"
              ]
            }
          }
        }
      },
      "imports": [
        "@openzeppelin/contracts/token/ERC20/IERC20.sol",
        "../interfaces/IEasyAuction.sol",
        "../libraries/SwapTypes.sol"
      ],
      "versionPragmas": [
        ">=0.7.2"
      ],
      "artifacts": [
        "AuctionUtils"
      ]
    },
    "/Users/antonasso/programming/opyn/perp-vault-templates/contracts/libraries/SwapTypes.sol": {
      "lastModificationDate": 1623424904634,
      "contentHash": "fb30204c55d5ec165e4fce00156dcdf7",
      "sourceName": "contracts/libraries/SwapTypes.sol",
      "solcConfig": {
        "version": "0.7.6",
        "settings": {
          "optimizer": {
            "enabled": false,
            "runs": 200
          },
          "outputSelection": {
            "*": {
              "*": [
                "abi",
                "evm.bytecode",
                "evm.deployedBytecode",
                "evm.methodIdentifiers"
              ],
              "": [
                "ast"
              ]
            }
          }
        }
      },
      "imports": [],
      "versionPragmas": [
        "^0.7.2"
      ],
      "artifacts": [
        "SwapTypes"
      ]
    },
    "/Users/antonasso/programming/opyn/perp-vault-templates/contracts/interfaces/IOracle.sol": {
      "lastModificationDate": 1623424904591,
      "contentHash": "4238ef36c86654e2e5eb410e46d6decb",
      "sourceName": "contracts/interfaces/IOracle.sol",
      "solcConfig": {
        "version": "0.7.6",
        "settings": {
          "optimizer": {
            "enabled": false,
            "runs": 200
          },
          "outputSelection": {
            "*": {
              "*": [
                "abi",
                "evm.bytecode",
                "evm.deployedBytecode",
                "evm.methodIdentifiers"
              ],
              "": [
                "ast"
              ]
            }
          }
        }
      },
      "imports": [],
      "versionPragmas": [
        "^0.7.2"
      ],
      "artifacts": [
        "IOracle"
      ]
    },
    "/Users/antonasso/programming/opyn/perp-vault-templates/contracts/interfaces/IOToken.sol": {
      "lastModificationDate": 1623424904598,
      "contentHash": "782ce14fc65eb0bc90cc0619181d1c6d",
      "sourceName": "contracts/interfaces/IOToken.sol",
      "solcConfig": {
        "version": "0.7.6",
        "settings": {
          "optimizer": {
            "enabled": false,
            "runs": 200
          },
          "outputSelection": {
            "*": {
              "*": [
                "abi",
                "evm.bytecode",
                "evm.deployedBytecode",
                "evm.methodIdentifiers"
              ],
              "": [
                "ast"
              ]
            }
          }
        }
      },
      "imports": [],
      "versionPragmas": [
        ">=0.7.2"
      ],
      "artifacts": [
        "IOToken"
      ]
    },
    "/Users/antonasso/programming/opyn/perp-vault-templates/contracts/interfaces/IWhitelist.sol": {
      "lastModificationDate": 1623424415868,
      "contentHash": "2e84f4cc7a3f377ca20b5c0e8b52f5f5",
      "sourceName": "contracts/interfaces/IWhitelist.sol",
      "solcConfig": {
        "version": "0.7.6",
        "settings": {
          "optimizer": {
            "enabled": false,
            "runs": 200
          },
          "outputSelection": {
            "*": {
              "*": [
                "abi",
                "evm.bytecode",
                "evm.deployedBytecode",
                "evm.methodIdentifiers"
              ],
              "": [
                "ast"
              ]
            }
          }
        }
      },
      "imports": [],
      "versionPragmas": [
        ">=0.7.2"
      ],
      "artifacts": [
        "IWhitelist"
      ]
    },
    "/Users/antonasso/programming/opyn/perp-vault-templates/contracts/interfaces/ISwap.sol": {
      "lastModificationDate": 1623424904612,
      "contentHash": "652c8aaa813a98aa7333667569008ef8",
      "sourceName": "contracts/interfaces/ISwap.sol",
      "solcConfig": {
        "version": "0.7.6",
        "settings": {
          "optimizer": {
            "enabled": false,
            "runs": 200
          },
          "outputSelection": {
            "*": {
              "*": [
                "abi",
                "evm.bytecode",
                "evm.deployedBytecode",
                "evm.methodIdentifiers"
              ],
              "": [
                "ast"
              ]
            }
          }
        }
      },
      "imports": [
        "../libraries/SwapTypes.sol"
      ],
      "versionPragmas": [
        "^0.7.2"
      ],
      "artifacts": [
        "ISwap"
      ]
    },
    "/Users/antonasso/programming/opyn/perp-vault-templates/contracts/interfaces/IEasyAuction.sol": {
      "lastModificationDate": 1623424904583,
      "contentHash": "f1be4a571ed6df058018b13f52bae57c",
      "sourceName": "contracts/interfaces/IEasyAuction.sol",
      "solcConfig": {
        "version": "0.7.6",
        "settings": {
          "optimizer": {
            "enabled": false,
            "runs": 200
          },
          "outputSelection": {
            "*": {
              "*": [
                "abi",
                "evm.bytecode",
                "evm.deployedBytecode",
                "evm.methodIdentifiers"
              ],
              "": [
                "ast"
              ]
            }
          }
        }
      },
      "imports": [],
      "versionPragmas": [
        ">=0.7.2"
      ],
      "artifacts": [
        "IEasyAuction"
      ]
    },
    "/Users/antonasso/programming/opyn/perp-vault-templates/contracts/mocks/MockPricer.sol": {
      "lastModificationDate": 1623424904768,
      "contentHash": "1ba0d5775ebc6b7a8dc3dcb620a51b01",
      "sourceName": "contracts/mocks/MockPricer.sol",
      "solcConfig": {
        "version": "0.7.6",
        "settings": {
          "optimizer": {
            "enabled": false,
            "runs": 200
          },
          "outputSelection": {
            "*": {
              "*": [
                "abi",
                "evm.bytecode",
                "evm.deployedBytecode",
                "evm.methodIdentifiers"
              ],
              "": [
                "ast"
              ]
            }
          }
        }
      },
      "imports": [
        "../interfaces/IOracle.sol"
      ],
      "versionPragmas": [
        "^0.7.2"
      ],
      "artifacts": [
        "MockPricer"
      ]
    },
    "/Users/antonasso/programming/opyn/perp-vault-templates/contracts/mocks/MockAction.sol": {
      "lastModificationDate": 1623424904652,
      "contentHash": "a6298731039611b45b84f130000833b5",
      "sourceName": "contracts/mocks/MockAction.sol",
      "solcConfig": {
        "version": "0.7.6",
        "settings": {
          "optimizer": {
            "enabled": false,
            "runs": 200
          },
          "outputSelection": {
            "*": {
              "*": [
                "abi",
                "evm.bytecode",
                "evm.deployedBytecode",
                "evm.methodIdentifiers"
              ],
              "": [
                "ast"
              ]
            }
          }
        }
      },
      "imports": [
        "../interfaces/IAction.sol",
        "@openzeppelin/contracts/token/ERC20/IERC20.sol"
      ],
      "versionPragmas": [
        "^0.7.0"
      ],
      "artifacts": [
        "MockAction"
      ]
    },
    "/Users/antonasso/programming/opyn/perp-vault-templates/contracts/mocks/MockSwap.sol": {
      "lastModificationDate": 1623424904777,
      "contentHash": "2eb48994a5899e928837bfd7fc49e34b",
      "sourceName": "contracts/mocks/MockSwap.sol",
      "solcConfig": {
        "version": "0.7.6",
        "settings": {
          "optimizer": {
            "enabled": false,
            "runs": 200
          },
          "outputSelection": {
            "*": {
              "*": [
                "abi",
                "evm.bytecode",
                "evm.deployedBytecode",
                "evm.methodIdentifiers"
              ],
              "": [
                "ast"
              ]
            }
          }
        }
      },
      "imports": [
        "../libraries/SwapTypes.sol",
        "../interfaces/ISwap.sol",
        "@openzeppelin/contracts/token/ERC20/IERC20.sol"
      ],
      "versionPragmas": [
        "^0.7.2"
      ],
      "artifacts": [
        "MockSwap"
      ]
    },
    "/Users/antonasso/programming/opyn/perp-vault-templates/contracts/mocks/MockPool.sol": {
      "lastModificationDate": 1623424904757,
      "contentHash": "33b5761c2d3dff0d896ac80f96ba2a36",
      "sourceName": "contracts/mocks/MockPool.sol",
      "solcConfig": {
        "version": "0.7.6",
        "settings": {
          "optimizer": {
            "enabled": false,
            "runs": 200
          },
          "outputSelection": {
            "*": {
              "*": [
                "abi",
                "evm.bytecode",
                "evm.deployedBytecode",
                "evm.methodIdentifiers"
              ],
              "": [
                "ast"
              ]
            }
          }
        }
      },
      "imports": [
        "@openzeppelin/contracts/token/ERC20/IERC20.sol"
      ],
      "versionPragmas": [
        "^0.7.0"
      ],
      "artifacts": [
        "MockPool"
      ]
    },
    "/Users/antonasso/programming/opyn/perp-vault-templates/contracts/mocks/MockWhitelist.sol": {
      "lastModificationDate": 1623424904803,
      "contentHash": "5d69a7b1ab7178afc8ede2af93492b22",
      "sourceName": "contracts/mocks/MockWhitelist.sol",
      "solcConfig": {
        "version": "0.7.6",
        "settings": {
          "optimizer": {
            "enabled": false,
            "runs": 200
          },
          "outputSelection": {
            "*": {
              "*": [
                "abi",
                "evm.bytecode",
                "evm.deployedBytecode",
                "evm.methodIdentifiers"
              ],
              "": [
                "ast"
              ]
            }
          }
        }
      },
      "imports": [
        "../interfaces/IWhitelist.sol"
      ],
      "versionPragmas": [
        "^0.7.0"
      ],
      "artifacts": [
        "MockWhitelist"
      ]
    },
    "/Users/antonasso/programming/opyn/perp-vault-templates/node_modules/@openzeppelin/contracts-upgradeable/drafts/EIP712Upgradeable.sol": {
      "lastModificationDate": 1622516806802,
      "contentHash": "561a5b469b2870291fdecd726e3f7501",
      "sourceName": "@openzeppelin/contracts-upgradeable/drafts/EIP712Upgradeable.sol",
      "solcConfig": {
        "version": "0.7.6",
        "settings": {
          "optimizer": {
            "enabled": false,
            "runs": 200
          },
          "outputSelection": {
            "*": {
              "*": [
                "abi",
                "evm.bytecode",
                "evm.deployedBytecode",
                "evm.methodIdentifiers"
              ],
              "": [
                "ast"
              ]
            }
          }
        }
      },
      "imports": [
        "../proxy/Initializable.sol"
      ],
      "versionPragmas": [
        ">=0.6.0 <0.8.0"
      ],
      "artifacts": [
        "EIP712Upgradeable"
      ]
    },
    "/Users/antonasso/programming/opyn/perp-vault-templates/node_modules/@openzeppelin/contracts-upgradeable/drafts/ERC20PermitUpgradeable.sol": {
      "lastModificationDate": 1622516806980,
      "contentHash": "3e510705706431f5c73bdc56d616424d",
      "sourceName": "@openzeppelin/contracts-upgradeable/drafts/ERC20PermitUpgradeable.sol",
      "solcConfig": {
        "version": "0.7.6",
        "settings": {
          "optimizer": {
            "enabled": false,
            "runs": 200
          },
          "outputSelection": {
            "*": {
              "*": [
                "abi",
                "evm.bytecode",
                "evm.deployedBytecode",
                "evm.methodIdentifiers"
              ],
              "": [
                "ast"
              ]
            }
          }
        }
      },
      "imports": [
        "../token/ERC20/ERC20Upgradeable.sol",
        "./IERC20PermitUpgradeable.sol",
        "../cryptography/ECDSAUpgradeable.sol",
        "../utils/CountersUpgradeable.sol",
        "./EIP712Upgradeable.sol",
        "../proxy/Initializable.sol"
      ],
      "versionPragmas": [
        ">=0.6.5 <0.8.0"
      ],
      "artifacts": [
        "ERC20PermitUpgradeable"
      ]
    },
    "/Users/antonasso/programming/opyn/perp-vault-templates/node_modules/@openzeppelin/contracts-upgradeable/drafts/IERC20PermitUpgradeable.sol": {
      "lastModificationDate": 1622516807246,
      "contentHash": "851cd6f51cf3b2cbebe86458c2d3d4c1",
      "sourceName": "@openzeppelin/contracts-upgradeable/drafts/IERC20PermitUpgradeable.sol",
      "solcConfig": {
        "version": "0.7.6",
        "settings": {
          "optimizer": {
            "enabled": false,
            "runs": 200
          },
          "outputSelection": {
            "*": {
              "*": [
                "abi",
                "evm.bytecode",
                "evm.deployedBytecode",
                "evm.methodIdentifiers"
              ],
              "": [
                "ast"
              ]
            }
          }
        }
      },
      "imports": [],
      "versionPragmas": [
        ">=0.6.0 <0.8.0"
      ],
      "artifacts": [
        "IERC20PermitUpgradeable"
      ]
    },
    "/Users/antonasso/programming/opyn/perp-vault-templates/node_modules/@openzeppelin/contracts-upgradeable/cryptography/ECDSAUpgradeable.sol": {
      "lastModificationDate": 1622516806799,
      "contentHash": "8fe21554560075593b87ae37a30dea42",
      "sourceName": "@openzeppelin/contracts-upgradeable/cryptography/ECDSAUpgradeable.sol",
      "solcConfig": {
        "version": "0.7.6",
        "settings": {
          "optimizer": {
            "enabled": false,
            "runs": 200
          },
          "outputSelection": {
            "*": {
              "*": [
                "abi",
                "evm.bytecode",
                "evm.deployedBytecode",
                "evm.methodIdentifiers"
              ],
              "": [
                "ast"
              ]
            }
          }
        }
      },
      "imports": [],
      "versionPragmas": [
        ">=0.6.0 <0.8.0"
      ],
      "artifacts": [
        "ECDSAUpgradeable"
      ]
    },
    "/Users/antonasso/programming/opyn/perp-vault-templates/node_modules/@openzeppelin/contracts-upgradeable/utils/CountersUpgradeable.sol": {
      "lastModificationDate": 1622516806769,
      "contentHash": "8cba95f8a22b2fb5aad5aa6cede94288",
      "sourceName": "@openzeppelin/contracts-upgradeable/utils/CountersUpgradeable.sol",
      "solcConfig": {
        "version": "0.7.6",
        "settings": {
          "optimizer": {
            "enabled": false,
            "runs": 200
          },
          "outputSelection": {
            "*": {
              "*": [
                "abi",
                "evm.bytecode",
                "evm.deployedBytecode",
                "evm.methodIdentifiers"
              ],
              "": [
                "ast"
              ]
            }
          }
        }
      },
      "imports": [
        "../math/SafeMathUpgradeable.sol"
      ],
      "versionPragmas": [
        ">=0.6.0 <0.8.0"
      ],
      "artifacts": [
        "CountersUpgradeable"
      ]
    },
    "/Users/antonasso/programming/opyn/perp-vault-templates/contracts/mocks/MockWETH.sol": {
      "lastModificationDate": 1623424904796,
      "contentHash": "b53217ed336f70069538310e53921157",
      "sourceName": "contracts/mocks/MockWETH.sol",
      "solcConfig": {
        "version": "0.7.6",
        "settings": {
          "optimizer": {
            "enabled": false,
            "runs": 200
          },
          "outputSelection": {
            "*": {
              "*": [
                "abi",
                "evm.bytecode",
                "evm.deployedBytecode",
                "evm.methodIdentifiers"
              ],
              "": [
                "ast"
              ]
            }
          }
        }
      },
      "imports": [
        "@openzeppelin/contracts-upgradeable/drafts/ERC20PermitUpgradeable.sol",
        "../interfaces/IWETH.sol"
      ],
      "versionPragmas": [
        "^0.7.0"
      ],
      "artifacts": [
        "MockWETH"
      ]
    },
    "/Users/antonasso/programming/opyn/perp-vault-templates/contracts/mocks/MockERC20.sol": {
      "lastModificationDate": 1623424904705,
      "contentHash": "d6743dbd936ddfa68918f9a40798f711",
      "sourceName": "contracts/mocks/MockERC20.sol",
      "solcConfig": {
        "version": "0.7.6",
        "settings": {
          "optimizer": {
            "enabled": false,
            "runs": 200
          },
          "outputSelection": {
            "*": {
              "*": [
                "abi",
                "evm.bytecode",
                "evm.deployedBytecode",
                "evm.methodIdentifiers"
              ],
              "": [
                "ast"
              ]
            }
          }
        }
      },
      "imports": [
        "@openzeppelin/contracts-upgradeable/drafts/ERC20PermitUpgradeable.sol"
      ],
      "versionPragmas": [
        "^0.7.0"
      ],
      "artifacts": [
        "MockERC20"
      ]
    },
    "/Users/antonasso/programming/opyn/perp-vault-templates/contracts/mocks/MockOToken.sol": {
      "lastModificationDate": 1623424904748,
      "contentHash": "472e47481787ea1128daa36f228dabba",
      "sourceName": "contracts/mocks/MockOToken.sol",
      "solcConfig": {
        "version": "0.7.6",
        "settings": {
          "optimizer": {
            "enabled": false,
            "runs": 200
          },
          "outputSelection": {
            "*": {
              "*": [
                "abi",
                "evm.bytecode",
                "evm.deployedBytecode",
                "evm.methodIdentifiers"
              ],
              "": [
                "ast"
              ]
            }
          }
        }
      },
      "imports": [
        "./MockERC20.sol"
      ],
      "versionPragmas": [
        "^0.7.0"
      ],
      "artifacts": [
        "MockOToken"
      ]
    },
    "/Users/antonasso/programming/opyn/perp-vault-templates/contracts/mocks/MockController.sol": {
      "lastModificationDate": 1623424904695,
      "contentHash": "e23d52fdc9604d9332b5c1236ac8de3a",
      "sourceName": "contracts/mocks/MockController.sol",
      "solcConfig": {
        "version": "0.7.6",
        "settings": {
          "optimizer": {
            "enabled": false,
            "runs": 200
          },
          "outputSelection": {
            "*": {
              "*": [
                "abi",
                "evm.bytecode",
                "evm.deployedBytecode",
                "evm.methodIdentifiers"
              ],
              "": [
                "ast"
              ]
            }
          }
        }
      },
      "imports": [
        "../interfaces/IPool.sol",
        "./MockERC20.sol"
      ],
      "versionPragmas": [
        "^0.7.0"
      ],
      "artifacts": [
        "MockController"
      ]
    },
    "/Users/antonasso/programming/opyn/perp-vault-templates/contracts/interfaces/IPool.sol": {
      "lastModificationDate": 1623424415832,
      "contentHash": "a46dc73141c80fd4aea3cfaa576b53c7",
      "sourceName": "contracts/interfaces/IPool.sol",
      "solcConfig": {
        "version": "0.7.6",
        "settings": {
          "optimizer": {
            "enabled": false,
            "runs": 200
          },
          "outputSelection": {
            "*": {
              "*": [
                "abi",
                "evm.bytecode",
                "evm.deployedBytecode",
                "evm.methodIdentifiers"
              ],
              "": [
                "ast"
              ]
            }
          }
        }
      },
      "imports": [],
      "versionPragmas": [
        "^0.7.2"
      ],
      "artifacts": [
        "IPool"
      ]
    },
    "/Users/antonasso/programming/opyn/perp-vault-templates/contracts/interfaces/IChainlink.sol": {
      "lastModificationDate": 1623424904553,
      "contentHash": "97572f61ad6bfb936c409cfdd93fae0f",
      "sourceName": "contracts/interfaces/IChainlink.sol",
      "solcConfig": {
        "version": "0.7.6",
        "settings": {
          "optimizer": {
            "enabled": false,
            "runs": 200
          },
          "outputSelection": {
            "*": {
              "*": [
                "abi",
                "evm.bytecode",
                "evm.deployedBytecode",
                "evm.methodIdentifiers"
              ],
              "": [
                "ast"
              ]
            }
          }
        }
      },
      "imports": [],
      "versionPragmas": [
        ">=0.6.0"
      ],
      "artifacts": [
        "IChainlink"
      ]
    },
    "/Users/antonasso/programming/opyn/perp-vault-templates/contracts/interfaces/IOtokenFactory.sol": {
      "lastModificationDate": 1623424904603,
      "contentHash": "dbb48335269a5cdaf918f2c329bce978",
      "sourceName": "contracts/interfaces/IOtokenFactory.sol",
      "solcConfig": {
        "version": "0.7.6",
        "settings": {
          "optimizer": {
            "enabled": false,
            "runs": 200
          },
          "outputSelection": {
            "*": {
              "*": [
                "abi",
                "evm.bytecode",
                "evm.deployedBytecode",
                "evm.methodIdentifiers"
              ],
              "": [
                "ast"
              ]
            }
          }
        }
      },
      "imports": [],
      "versionPragmas": [
        ">=0.7.2"
      ],
      "artifacts": [
        "IOtokenFactory"
      ]
    },
    "/Users/antonasso/programming/opyn/perp-vault-templates/contracts/mocks/MockOpynOracle.sol": {
      "lastModificationDate": 1623424904715,
      "contentHash": "bdaf6b5c1c868dd7774f1acd8a858b25",
      "sourceName": "contracts/mocks/MockOpynOracle.sol",
      "solcConfig": {
        "version": "0.7.6",
        "settings": {
          "optimizer": {
            "enabled": false,
            "runs": 200
          },
          "outputSelection": {
            "*": {
              "*": [
                "abi",
                "evm.bytecode",
                "evm.deployedBytecode",
                "evm.methodIdentifiers"
              ],
              "": [
                "ast"
              ]
            }
          }
        }
      },
      "imports": [],
      "versionPragmas": [
        ">=0.6.0"
      ],
      "artifacts": [
        "MockOpynOracle"
      ]
    },
    "/Users/antonasso/programming/opyn/perp-vault-templates/contracts/mocks/MockOracle.sol": {
      "lastModificationDate": 1623424904731,
      "contentHash": "9bb9ffe7d8f5912c8561e7a334f448ee",
      "sourceName": "contracts/mocks/MockOracle.sol",
      "solcConfig": {
        "version": "0.7.6",
        "settings": {
          "optimizer": {
            "enabled": false,
            "runs": 200
          },
          "outputSelection": {
            "*": {
              "*": [
                "abi",
                "evm.bytecode",
                "evm.deployedBytecode",
                "evm.methodIdentifiers"
              ],
              "": [
                "ast"
              ]
            }
          }
        }
      },
      "imports": [],
      "versionPragmas": [
        ">=0.6.0"
      ],
      "artifacts": [
        "MockOracle"
      ]
    }
  }
}
